invagination/__init__.py
invagination/delamination.py
invagination/ellipsoid.py
invagination/morphometry.py
invagination/plots.py
invagination/toolbox.py
invagination/version.py
invagination-0.0.2.dist-info/LICENSE
invagination-0.0.2.dist-info/METADATA
invagination-0.0.2.dist-info/WHEEL
invagination-0.0.2.dist-info/top_level.txt
invagination-0.0.2.dist-info/RECORD
